dbt_subdocs/__init__.py
dbt_subdocs/__main__.py
dbt_subdocs/dtos.py
dbt_subdocs/usecase/__init__.py
dbt_subdocs/usecase/edit_catalog.py
dbt_subdocs/usecase/edit_manifest.py
dbt_subdocs-0.1.1.dist-info/entry_points.txt
dbt_subdocs-0.1.1.dist-info/LICENSE
dbt_subdocs-0.1.1.dist-info/WHEEL
dbt_subdocs-0.1.1.dist-info/METADATA
dbt_subdocs-0.1.1.dist-info/RECORD
