Metadata-Version: 2.1
Name: dbt-subdocs
Version: 0.1.1
Summary: dbt-subdocs is a python CLI you can used to generate a dbt-docs for a subset of your dbt project
Home-page: https://github.com/jb-delafosse/dbt-subdocs
License: MIT
Author: jb-delafosse
Author-email: hello@jb-delafosse.com
Requires-Python: >=3.9,<4.0
Classifier: Development Status :: 3 - Alpha
Classifier: Intended Audience :: Developers
Classifier: License :: OSI Approved :: MIT License
Classifier: Operating System :: OS Independent
Classifier: Programming Language :: Python :: 3
Classifier: Programming Language :: Python :: 3.9
Classifier: Topic :: Software Development :: Libraries :: Python Modules
Requires-Dist: dbt-core (>=1.0.1,<2.0.0)
Requires-Dist: rich (>=10.14.0,<11.0.0)
Requires-Dist: typer[all] (>=0.4.0,<0.5.0)
Project-URL: Repository, https://github.com/jb-delafosse/dbt-subdocs
